{
    "version": 1,
    "all_bricks": {
        "1": {
            "submit_time": [
                1773700131
            ],
            "type": 4,
            "review_day": [
                1773720000,
                1773979200,
                1774238400,
                1774843200,
                1776052800,
                1778817600
            ]
        },
        "838": {
            "submit_time": [
                1773703200
            ],
            "type": 4,
            "review_day": [
                1773720000,
                1773979200,
                1774238400,
                1774843200,
                1776052800,
                1778817600
            ]
        }
    }
}